Metadata-Version: 2.1
Name: python-telegram-allure-notify
Version: 1.1
Summary: AllureBot
Author-email: gorelov2895@yandex.ru
